systempy/__init__.py
systempy/py.typed
systempy/target.py
systempy/target_meta.py
systempy/libsystempy/__init__.py
systempy/libsystempy/callback_plan.py
systempy/libsystempy/class_role.py
systempy/libsystempy/configuration.py
systempy/libsystempy/constants.py
systempy/libsystempy/creation.py
systempy/libsystempy/enums.py
systempy/libsystempy/extraction.py
systempy/libsystempy/handler_type.py
systempy/libsystempy/hook_registry.py
systempy/libsystempy/local_dataclasses.py
systempy/libsystempy/local_typing.py
systempy/libsystempy/misc.py
systempy/libsystempy/register.py
systempy/libsystempy/thread_exception.py
systempy/libsystempy/weak_queue.py
systempy/unit/__init__.py
systempy/unit/_compat_signal.py
systempy/unit/daemon.py
systempy/unit/event_wait.py
systempy/unit/loop.py
systempy/unit/scripting.py
systempy/unit/unit.py
systempy/unit/ext/__init__.py
systempy/unit/ext/celery.py
systempy/unit/ext/pretty_repl.py
systempy/unit/ext/ptrepl.py
systempy/unit/ext/starlette.py
systempy/unit/ext/target_ext.py
systempy/unit/repl/__init__.py
systempy/unit/repl/handle_interrupt.py
systempy/unit/repl/mixins.py
systempy/unit/repl/repl.py
systempy-0.1.6.dist-info/licenses/LICENSE
systempy-0.1.6.dist-info/METADATA
systempy-0.1.6.dist-info/WHEEL
systempy-0.1.6.dist-info/top_level.txt
systempy-0.1.6.dist-info/zip-safe
systempy-0.1.6.dist-info/RECORD
