Metadata-Version: 2.4
Name: systempy
Version: 0.1.6
Summary: Python application component initialization system
Home-page: https://github.com/kai3341/systemPY
Author: kai3341
License-Expression: MIT
Keywords: asyncio,graceful,init,initialization,shutdown,manager
Classifier: Development Status :: 4 - Beta
Classifier: Intended Audience :: Developers
Classifier: Programming Language :: Python :: 3 :: Only
Classifier: Programming Language :: Python :: 3.9
Classifier: Programming Language :: Python :: 3.10
Classifier: Programming Language :: Python :: 3.11
Classifier: Programming Language :: Python :: 3.12
Classifier: Programming Language :: Python :: 3.13
Classifier: Programming Language :: Python :: 3.14
Classifier: Topic :: Software Development :: Libraries
Classifier: Topic :: Software Development :: Libraries :: Application Frameworks
Classifier: Topic :: Software Development :: Libraries :: Python Modules
Classifier: Typing :: Typed
Requires-Python: >=3.9
License-File: LICENSE
Requires-Dist: typing-extensions
Provides-Extra: extra
Requires-Dist: ptpython>=3.0.30; extra == "extra"
Dynamic: home-page
Dynamic: license-file
